pygameweb/__init__.py
pygameweb/app.py
pygameweb/cache.py
pygameweb/config.py
pygameweb/db.py
pygameweb/models.py
pygameweb/run.py
pygameweb/sanitize.py
pygameweb/tasks/__init__.py
pygameweb/tasks/models.py
pygameweb/tasks/worker.py
pygameweb/thumb/__init__.py
pygameweb/thumb/views.py
pygameweb-0.0.6.data/data/alembic.ini
pygameweb-0.0.6.dist-info/LICENSE
pygameweb-0.0.6.dist-info/METADATA
pygameweb-0.0.6.dist-info/WHEEL
pygameweb-0.0.6.dist-info/entry_points.txt
pygameweb-0.0.6.dist-info/top_level.txt
pygameweb-0.0.6.dist-info/RECORD
