Metadata-Version: 2.1
Name: pygameweb
Version: 0.0.6
Summary: Pygame.org website.
Home-page: https://github.com/pygame/pygameweb
Author: Rene Dudfield
Author-email: renesd@gmail.com
License: BSD
Platform: UNKNOWN
Classifier: Development Status :: 1 - Planning
Classifier: License :: OSI Approved :: BSD License
Classifier: Programming Language :: Python :: 3
Classifier: Programming Language :: Python :: 3.6
Requires-Dist: python-dotenv
Requires-Dist: pyquery
Requires-Dist: sphinx
Requires-Dist: scipy
Requires-Dist: numpy
Requires-Dist: python-slugify
Requires-Dist: flask-limiter
Requires-Dist: flask-admin
Requires-Dist: flask-bootstrap
Requires-Dist: flask-debugtoolbar
Requires-Dist: Flask
Requires-Dist: pygments
Requires-Dist: pandas
Requires-Dist: flask-nav
Requires-Dist: scikit-learn
Requires-Dist: dnspython
Requires-Dist: feedparser
Requires-Dist: click
Requires-Dist: Flask-Caching
Requires-Dist: Flask-Gravatar
Requires-Dist: alembic
Requires-Dist: Flask-WTF
Requires-Dist: flask-sqlalchemy-session
Requires-Dist: Flask-Security-Fork (==2.0.1)
Requires-Dist: bcrypt
Requires-Dist: pq
Requires-Dist: ghdiff
Requires-Dist: psycopg2
